pychell/.DS_Store
pychell/__init__.py
pychell/config.py
pychell/driver.py
pychell/gadfly_stylesheet.mplstyle
pychell/maths.py
pychell/stutilis.py
pychell/stutils.py
pychell/utils.py
pychell/__pycache__/__init__.cpython-37.pyc
pychell/__pycache__/__init__.cpython-38.pyc
pychell/__pycache__/config.cpython-37.pyc
pychell/__pycache__/config.cpython-38.pyc
pychell/__pycache__/driver.cpython-37.pyc
pychell/__pycache__/driver.cpython-38.pyc
pychell/__pycache__/maths.cpython-37.pyc
pychell/__pycache__/maths.cpython-38.pyc
pychell/__pycache__/nelder_mead.cpython-37.pyc
pychell/__pycache__/parameters.cpython-37.pyc
pychell/__pycache__/utils.cpython-37.pyc
pychell/__pycache__/utils.cpython-38.pyc
pychell/data/.DS_Store
pychell/data/__init__.py
pychell/data/chiron.py
pychell/data/data.py
pychell/data/ishell.py
pychell/data/minervaaustralis.py
pychell/data/minervanorth.py
pychell/data/nirspec.py
pychell/data/parsers.py
pychell/data/parvi.py
pychell/data/simulated.py
pychell/data/__pycache__/__init__.cpython-37.pyc
pychell/data/__pycache__/__init__.cpython-38.pyc
pychell/data/__pycache__/chiron.cpython-37.pyc
pychell/data/__pycache__/chiron.cpython-38.pyc
pychell/data/__pycache__/data.cpython-37.pyc
pychell/data/__pycache__/data.cpython-38.pyc
pychell/data/__pycache__/ishell.cpython-37.pyc
pychell/data/__pycache__/ishell.cpython-38.pyc
pychell/data/__pycache__/minervaaustralis.cpython-37.pyc
pychell/data/__pycache__/minervaaustralis.cpython-38.pyc
pychell/data/__pycache__/minervanorth.cpython-37.pyc
pychell/data/__pycache__/minervanorth.cpython-38.pyc
pychell/data/__pycache__/parsers.cpython-37.pyc
pychell/data/__pycache__/parsers.cpython-38.pyc
pychell/data/__pycache__/parvi.cpython-37.pyc
pychell/data/__pycache__/parvi.cpython-38.pyc
pychell/data/__pycache__/simulated.cpython-37.pyc
pychell/data/__pycache__/simulated.cpython-38.pyc
pychell/orbits/.DS_Store
pychell/orbits/__init__.py
pychell/orbits/gls.py
pychell/orbits/rvdata.py
pychell/orbits/rvkernels.py
pychell-1.0.3.dist-info/METADATA
pychell-1.0.3.dist-info/WHEEL
pychell-1.0.3.dist-info/top_level.txt
pychell-1.0.3.dist-info/RECORD
