Metadata-Version: 2.1
Name: pychell
Version: 1.0.3
Summary: Reduce echelle spectra and generate radial velocities
Home-page: https://github.com/astrobc1/pychell
Author: Bryson Cale
Author-email: bryson.cale1@gmail.com
License: UNKNOWN
Platform: UNKNOWN
Classifier: Programming Language :: Python :: 3.6
Classifier: Operating System :: Unix
Classifier: License :: OSI Approved :: GNU General Public License v3 (GPLv3)
Requires-Python: >=3.6
Requires-Dist: astropy (>=4.0)
Requires-Dist: llc (>=0.2)
Requires-Dist: barycorrpy (==0.3.4)
Requires-Dist: tqdm (>=4.48.2)
Requires-Dist: numba (>=0.48)
Requires-Dist: numpy (>=1.18)
Requires-Dist: optimparameters (>=1.0.6)
Requires-Dist: robustneldermead (>=1.4)
Requires-Dist: matplotlib (>=3.1.3)
Requires-Dist: googledrivedownloader (>=0.4)
Requires-Dist: scipy (>=1.4.1)
Requires-Dist: joblib (>=0.14.1)
Requires-Dist: scikit-learn (>=0.22.2)
Requires-Dist: torch (>=1.5.1)
Requires-Dist: streamlit (>=0.73.1)
Requires-Dist: plotly (>=4.14.1)
Requires-Dist: emcee (>=3.0.2)
Requires-Dist: bayesoptimize (>=1.0.1)
